{
  "hash": "3b53f27ac746ca0839909862e6b5582e",
  "result": {
    "engine": "knitr",
    "markdown": "---\nexecute: \n  echo: true\n  eval: false\n  warning: false\n---\n\n\n# Appendices {.unnumbered}\n\nFigures in the paper were created with the following code:\n\n\n::: {.cell}\n\n```{.r .cell-code}\n# Load required packages\nlibrary(tidyverse)\nlibrary(patchwork)\nlibrary(here)\n\n\n# Load plots\ngeo_instructors <- readRDS(here(\"products\", \"plots\", \"instructors_geodistro.rds\"))\ngeo_workshops <- readRDS(here(\"products\", \"plots\", \"workshops_geodistro.rds\"))\nexperience <- readRDS(here(\"products\", \"plots\", \"experience_with_workshop.rds\"))\n\n\n# Create multi-panel figure\nfinal_fig <- wrap_plots(\n    wrap_plots(\n        geo_instructors + \n            theme(plot.margin = margin(l = -40, r = -20)) +\n            labs(\n                title = \"Carpentries-certified instructors\"\n            ), \n        geo_workshops + \n            theme(plot.margin = margin(l = -40, r = -20)) +\n            labs(title = \"Bioconductor Carpentry workshops\")\n    ),\n    experience,\n    nrow = 2,\n    heights = c(2, 1)\n) +\n    plot_annotation(tag_levels = \"A\")\n\nfinal_fig\n\nggsave(\n    final_fig, \n    filename = here(\"products\", \"figs\", \"fig_carpentries.png\"),\n    width = 11, height = 7, dpi = 300\n)\n\nggsave(\n    final_fig, \n    filename = here(\"products\", \"figs\", \"fig_carpentries.pdf\"),\n    width = 11, height = 7\n)\n```\n:::\n\n\n## Session info {.unnumbered}\n\nThis document was created under the following conditions:\n\n\n::: {.cell}\n::: {.cell-output .cell-output-stdout}\n\n```\n─ Session info ───────────────────────────────────────────────────────────────\n setting  value\n version  R version 4.4.1 (2024-06-14)\n os       Ubuntu 22.04.4 LTS\n system   x86_64, linux-gnu\n ui       X11\n language (EN)\n collate  en_US.UTF-8\n ctype    en_US.UTF-8\n tz       Arctic/Longyearbyen\n date     2025-03-09\n pandoc   3.1.11 @ /opt/quarto/bin/tools/ (via rmarkdown)\n\n─ Packages ───────────────────────────────────────────────────────────────────\n package     * version date (UTC) lib source\n cli           3.6.3   2024-06-21 [1] CRAN (R 4.4.1)\n digest        0.6.36  2024-06-23 [1] CRAN (R 4.4.1)\n evaluate      0.24.0  2024-06-10 [1] CRAN (R 4.4.1)\n fastmap       1.2.0   2024-05-15 [1] CRAN (R 4.4.1)\n htmltools     0.5.8.1 2024-04-04 [1] CRAN (R 4.4.1)\n htmlwidgets   1.6.4   2023-12-06 [1] CRAN (R 4.4.1)\n jsonlite      1.8.8   2023-12-04 [1] CRAN (R 4.4.1)\n knitr         1.48    2024-07-07 [1] CRAN (R 4.4.1)\n rlang         1.1.4   2024-06-04 [1] CRAN (R 4.4.1)\n rmarkdown     2.27    2024-05-17 [1] CRAN (R 4.4.1)\n sessioninfo   1.2.2   2021-12-06 [1] CRAN (R 4.4.1)\n xfun          0.46    2024-07-18 [1] CRAN (R 4.4.1)\n yaml          2.3.9   2024-07-05 [1] CRAN (R 4.4.1)\n\n [1] /home/faalm/R/x86_64-pc-linux-gnu-library/4.4\n [2] /usr/local/lib/R/site-library\n [3] /usr/lib/R/site-library\n [4] /usr/lib/R/library\n\n──────────────────────────────────────────────────────────────────────────────\n```\n\n\n:::\n:::\n",
    "supporting": [],
    "filters": [
      "rmarkdown/pagebreak.lua"
    ],
    "includes": {},
    "engineDependencies": {},
    "preserve": {},
    "postProcess": true
  }
}